Metadata-Version: 2.1
Name: atimer
Version: 1.0.1
Summary: atimer - timer library for asyncio
Home-page: https://wrobell.dcmod.org/atimer/
Author: Artur Wroblewski
Author-email: wrobell@riseup.net
License: GPLv3+
Project-URL: Source Code, https://gitlab.com/n23/atimer
Project-URL: Bug tracker, https://gitlab.com/n23/atimer/issues
Platform: UNKNOWN
Classifier: Topic :: Software Development :: Libraries
Classifier: License :: OSI Approved :: GNU General Public License v3 or later (GPLv3+)
Classifier: Programming Language :: Python :: 3
Classifier: Development Status :: 5 - Production/Stable
Requires-Python: >=3.8
Provides-Extra: tests
License-File: COPYING
